flask_spyc_login/__init__.py
flask_spyc_login/tools.py
Flask_SPYC_Login-0.0.0.dist-info/LICENSE
Flask_SPYC_Login-0.0.0.dist-info/METADATA
Flask_SPYC_Login-0.0.0.dist-info/WHEEL
Flask_SPYC_Login-0.0.0.dist-info/top_level.txt
Flask_SPYC_Login-0.0.0.dist-info/RECORD
