Metadata-Version: 2.1
Name: Flask-SPYC-Login
Version: 0.0.0
Summary: SPYC-Login Python Backend SDK
Home-page: https://github.com
Author: spyc
Author-email: unknown@gmail.com
License: MIT
Platform: UNKNOWN
Classifier: Programming Language :: Python :: 3
Classifier: License :: OSI Approved :: MIT License
Classifier: Operating System :: OS Independent
Requires-Dist: Flask
Requires-Dist: requests
